{
  "description": "Classes to mask at inference time due to confusion patterns (auto-generated by curation)",
  "threshold_used": "confusion_threshold=0.5, quality=70.0/85.0",
  "masked_class_ids": [4, 5, 6, 10, 11, 14, 15, 16, 17, 20, 22, 25, 28, 33, 34, 37, 41, 44],
  "masked_class_names": [
    "EVENING",
    "EYE",
    "GOODBYE",
    "HELLO",
    "HIS",
    "HOW",
    "MY",
    "NECK",
    "NEED",
    "PAIN",
    "PREGNANT",
    "SHOULDER",
    "SNEEZE",
    "THERMOMETER",
    "THEY",
    "WHEELCHAIR",
    "WHO",
    "YOUR"
  ],
  "effective_classes": 27
}
